chimac/__init__.py
chimac/augmentor.py
chimac/chimac.py
chimac/utils/__init__.py
chimac/utils/adjust_sampler.py
chimac/utils/image_ops.py
chimac/utils/logger.py
chimac/utils/seeder.py
chimac-0.3.7.dist-info/licenses/LICENSE
chimac-0.3.7.dist-info/METADATA
chimac-0.3.7.dist-info/WHEEL
chimac-0.3.7.dist-info/entry_points.txt
chimac-0.3.7.dist-info/top_level.txt
chimac-0.3.7.dist-info/RECORD
