Metadata-Version: 2.4
Name: chimac
Version: 0.3.7
Summary: Chi-square based Class Imbalance Mitigation Algorithm for Controlled Augmentation
Author-email: Madhav Arora <contact.madhav.arora@gmail.com>
License: Copyright 2025 NextGenAI-Lab
Project-URL: Homepage, https://github.com/NextGenAI-Lab/ChiMAC
Project-URL: Repository, https://github.com/NextGenAI-Lab/ChiMAC
Project-URL: Issues, https://github.com/NextGenAI-Lab/ChiMAC/issues
Requires-Python: >=3.9
License-File: LICENSE
Requires-Dist: filelock>=3.0.0
Requires-Dist: fsspec>=2023.1.0
Requires-Dist: jinja2>=3.0.0
Requires-Dist: markdown-it-py>=3.0.0
Requires-Dist: markupsafe>=2.0.0
Requires-Dist: mdurl>=0.1.0
Requires-Dist: mpmath>=1.0.0
Requires-Dist: networkx>=3.0.0
Requires-Dist: numpy>=1.21.0
Requires-Dist: pillow>=8.0.0
Requires-Dist: pygments>=2.10.0
Requires-Dist: rich>=12.0.0
Requires-Dist: sympy>=1.10.0
Requires-Dist: torch<3.0.0,>=2.0.0
Requires-Dist: torchvision<1.0.0,>=0.15.0
Requires-Dist: tqdm>=4.60.0
Requires-Dist: typing-extensions>=4.0.0
Provides-Extra: cuda
Requires-Dist: nvidia-cublas-cu12; extra == "cuda"
Requires-Dist: nvidia-cuda-cupti-cu12; extra == "cuda"
Requires-Dist: nvidia-cuda-nvrtc-cu12; extra == "cuda"
Requires-Dist: nvidia-cuda-runtime-cu12; extra == "cuda"
Requires-Dist: nvidia-cudnn-cu12; extra == "cuda"
Requires-Dist: nvidia-cufft-cu12; extra == "cuda"
Requires-Dist: nvidia-cufile-cu12; extra == "cuda"
Requires-Dist: nvidia-curand-cu12; extra == "cuda"
Requires-Dist: nvidia-cusolver-cu12; extra == "cuda"
Requires-Dist: nvidia-cusparse-cu12; extra == "cuda"
Requires-Dist: nvidia-cusparselt-cu12; extra == "cuda"
Requires-Dist: nvidia-nccl-cu12; extra == "cuda"
Requires-Dist: nvidia-nvjitlink-cu12; extra == "cuda"
Requires-Dist: nvidia-nvtx-cu12; extra == "cuda"
Requires-Dist: triton>=2.0.0; extra == "cuda"
Provides-Extra: dev
Requires-Dist: pytest>=7.0.0; extra == "dev"
Requires-Dist: pytest-cov>=4.0.0; extra == "dev"
Requires-Dist: black>=22.0.0; extra == "dev"
Requires-Dist: isort>=5.10.0; extra == "dev"
Requires-Dist: flake8>=5.0.0; extra == "dev"
Requires-Dist: mypy>=1.0.0; extra == "dev"
Provides-Extra: docs
Requires-Dist: sphinx>=5.0.0; extra == "docs"
Requires-Dist: sphinx-rtd-theme>=1.0.0; extra == "docs"
Requires-Dist: myst-parser>=0.18.0; extra == "docs"
Provides-Extra: all
Requires-Dist: chimac[cuda,dev,docs]; extra == "all"
Dynamic: license-file
